beliefmatching/__init__.py
beliefmatching/_version.py
beliefmatching/belief_matching.py
beliefmatching/sinter_belief_matching.py
beliefmatching-0.2.0.dist-info/licenses/LICENSE
beliefmatching-0.2.0.dist-info/METADATA
beliefmatching-0.2.0.dist-info/WHEEL
beliefmatching-0.2.0.dist-info/top_level.txt
beliefmatching-0.2.0.dist-info/RECORD
