Metadata-Version: 2.4
Name: beliefmatching
Version: 0.2.0
Summary: A package for decoding quantum error correcting codes using belief-matching.
Home-page: https://github.com/oscarhiggott/BeliefMatching
Author: Oscar Higgott
License-File: LICENSE
Requires-Dist: stim
Requires-Dist: pymatching>=2.0.1
Requires-Dist: ldpc
Requires-Dist: sinter>=1.11
Requires-Dist: numpy<=2.2.6
Dynamic: author
Dynamic: description
Dynamic: description-content-type
Dynamic: home-page
Dynamic: license-file
Dynamic: requires-dist
Dynamic: summary
